{
    "_id": "SyrupClassInfo",
    "_name": "SyrupClassInfo",
    "_schema": "SyrupClassInfoSchema",
    "_inherit": ["SyrupComponent"],
    "_core": true,
    "metamodel": {
        "type": "object",
        "readOnly": true,
        "mandatory": true,
        "default": {}
    },
    "model": {
        "type": "object",
        "readOnly": true,
        "mandatory": true,
        "default": {}
    },
    "property": {
        "params": [{
                "name": "name",
                "type": "string"
            }],
        "result": "object"
    },
    "properties": {
        "result": "array"
    },
    "link": {
        "params": [{
                "name": "name",
                "type": "string"
            }],
        "result": "object"
    },
    "links": {
        "result": "array"
    },
    "method": {
        "params": [{
                "name": "name",
                "type": "string"
            }],
        "result": "object"
    },
    "methods": {
        "result": "array"
    },
    "collection": {
        "params": [{
                "name": "name",
                "type": "string"
            }],
        "result": "object"
    },
    "collections": {
        "result": "array"
    },
    "event": {
        "params": [{
                "name": "name",
                "type": "string"
            }],
        "result": "object"
    },
    "events": {
        "result": "array"
    }
}