{
  "_id": "m1d0f21f41e1af88",
  "name": "class-runtime-system-osgi",
  "description": "OSGi-like system",
  "version": "1.0.0",
  "behaviors": {
    "182c51edc31ad97": {
      "_id": "182c51edc31ad97",
      "component": "RuntimeSystemOSGi",
      "state": "uninstall",
      "action": "function uninstall() { \n\tthis.require('runtime').uninstall(this.id());\n}",
      "useCoreAPI": false,
      "core": true
    },
    "14b77144911ce48": {
      "_id": "14b77144911ce48",
      "component": "RuntimeSystemOSGi",
      "state": "bundle",
      "action": "function bundle() { \n\tvar result = '',\n\tsystem = [];\n\t\n\tsystems = $db.RuntimeSystem.find({\n    '_id': this.id()\n  });\n  \n  if (systems.length) {\n    result = JSON.stringify(systems[0]);\n  }\n  \n\treturn result;\n}",
      "useCoreAPI": true,
      "core": true
    }
  },
  "schemas": {
    "145fe10c7514298": {
      "_id": "145fe10c7514298",
      "_name": "RuntimeSystemOSGi",
      "_inherit": [
        "RuntimeComponent"
      ],
      "_core": true,
      "state": "property",
      "location": "property",
      "start": "method",
      "stop": "method",
      "uninstall": "method",
      "bundle": "method"
    }
  },
  "models": {
    "1b2811b092143f5": {
      "_id": "1b2811b092143f5",
      "_name": "RuntimeSystemOSGi",
      "start": {},
      "stop": {},
      "_core": true,
      "state": {
        "type": "string",
        "readOnly": false,
        "mandatory": false,
        "default": "none"
      },
      "location": {
        "type": "string",
        "readOnly": false,
        "mandatory": false,
        "default": ""
      },
      "uninstall": {},
      "bundle": {
        "result": "string"
      }
    }
  },
  "types": {},
  "components": {},
  "master": false,
  "subsystem": false
}